aivtu/__init__.py
aivtu/ann.py
aivtu/aostar.py
aivtu/astar.py
aivtu/ce.py
aivtu/em.py
aivtu/id3.py
aivtu/knn.py
aivtu/main.py
aivtu/nb.py
aivtu/reg.py
aivtu-8.dist-info/METADATA
aivtu-8.dist-info/WHEEL
aivtu-8.dist-info/top_level.txt
aivtu-8.dist-info/RECORD
