Metadata-Version: 2.1
Name: aivtu
Version: 8
Summary: AI/ML programs
Author: Sanjay R
Author-email: <sanjay66r@gmail.com>
Keywords: vtu
Classifier: Development Status :: 1 - Planning
Classifier: Intended Audience :: Developers
Classifier: Programming Language :: Python :: 3
Classifier: Operating System :: Unix
Classifier: Operating System :: MacOS :: MacOS X
Classifier: Operating System :: Microsoft :: Windows
